README.rst
setup.py
pysunsetwx/__init__.py
pysunsetwx/pysunsetwx.py
pysunsetwx.egg-info/PKG-INFO
pysunsetwx.egg-info/SOURCES.txt
pysunsetwx.egg-info/dependency_links.txt
pysunsetwx.egg-info/requires.txt
pysunsetwx.egg-info/top_level.txt
pysunsetwx/src/__init__.py
pysunsetwx/src/api.py
pysunsetwx/src/errors.py
pysunsetwx/src/liblogging.py
pysunsetwx/src/settings.py