Metadata-Version: 1.2
Name: pysunsetwx
Version: 1.0.0b1
Summary: A Python wrapper for the SunsetWx Sunburst REST API
Home-page: https://github.com/salvoventura/pysunsetwx
Author: salvatore ventura
Author-email: salvoventura@gmail.com
License: MIT
Keywords: pysunsetwx,rest,api,python,wrapper,development,sunsetwx.com,photography
Platform: UNKNOWN
Classifier: Development Status :: 4 - Beta
Classifier: Intended Audience :: Developers
Classifier: License :: OSI Approved :: MIT License
Classifier: Programming Language :: Python :: 2.7
Classifier: Programming Language :: Python :: 3.5
Classifier: Programming Language :: Python :: 3.6
Classifier: Programming Language :: Python :: 3.7
Requires-Python: >=2.7
